wakeps4onbt/__init__.py
wakeps4onbt/wakeps4onbt.py
pywakeps4onbt-0.8.0.dist-info/LICENSE
pywakeps4onbt-0.8.0.dist-info/METADATA
pywakeps4onbt-0.8.0.dist-info/WHEEL
pywakeps4onbt-0.8.0.dist-info/top_level.txt
pywakeps4onbt-0.8.0.dist-info/RECORD
